{"이미지 정보":{"이미지 식별자":564236,"이미지 높이":1066,"이미지 파일명":"_98Z5559.jpg","이미지 너비":800},"데이터셋 정보":{"파일 생성일자":"2020-10-19 14:51:42","데이터셋 상세설명":{"렉트좌표":{"아우터":[{}],"하의":[{"X좌표":277.0,"Y좌표":638.5,"가로":192,"세로":251}],"원피스":[{}],"상의":[{"X좌표":208.0,"Y좌표":178.5,"가로":246,"세로":536}]},"폴리곤좌표":{"아우터":[{}],"하의":[{"Y좌표9":881.0,"X좌표15":359.5,"X좌표14":391.5,"X좌표13":438.5,"X좌표12":453.5,"X좌표11":456.5,"Y좌표4":787.0,"X좌표10":469.5,"Y좌표3":737.0,"Y좌표2":706.0,"Y좌표1":662.0,"Y좌표8":888.0,"Y좌표7":890.0,"Y좌표6":873.0,"Y좌표5":837.0,"Y좌표15":641.0,"Y좌표14":639.0,"X좌표8":394.5,"X좌표9":443.5,"Y좌표11":747.0,"Y좌표10":832.0,"Y좌표13":672.0,"Y좌표12":692.0,"X좌표2":288.5,"X좌표3":283.5,"X좌표1":308.5,"X좌표6":294.5,"X좌표7":322.5,"X좌표4":277.5,"X좌표5":282.5}],"원피스":[{}],"상의":[{"Y좌표9":704.0,"Y좌표22":194.0,"Y좌표21":180.0,"Y좌표20":179.0,"X좌표19":383.5,"X좌표18":408.5,"X좌표17":430.5,"X좌표16":423.5,"X좌표15":427.5,"X좌표14":436.5,"X좌표13":454.5,"X좌표12":445.5,"X좌표11":416.5,"Y좌표4":361.0,"X좌표10":349.5,"Y좌표3":309.0,"Y좌표2":264.0,"Y좌표1":238.0,"Y좌표8":636.0,"Y좌표7":577.0,"Y좌표6":518.0,"Y좌표5":444.0,"Y좌표15":462.0,"Y좌표14":510.0,"X좌표8":245.5,"Y좌표17":295.0,"X좌표9":272.5,"Y좌표16":349.0,"Y좌표11":712.0,"Y좌표10":715.0,"Y좌표13":648.0,"Y좌표12":687.0,"X좌표22":309.5,"X좌표2":270.5,"X좌표21":329.5,"X좌표3":250.5,"X좌표20":364.5,"X좌표1":285.5,"X좌표6":208.5,"Y좌표19":197.0,"X좌표7":225.5,"Y좌표18":249.0,"X좌표4":230.5,"X좌표5":210.5}]},"라벨링":{"스타일":[{"스타일":"모던","서브스타일":"스트리트"}],"아우터":[{}],"하의":[{"색상":"와인","카테고리":"래깅스","소재":["스판덱스"],"프린트":["무지"],"핏":"스키니"}],"원피스":[{}],"상의":[{"기장":"롱","색상":"와인","서브색상":"블랙","카테고리":"후드티","소매기장":"긴팔","소재":["저지"],"프린트":["무지"],"핏":"루즈"}]}},"파일 번호":564236,"파일 이름":"_98Z5559.jpg"}}